Workbook

Sheet Risk Register
A1: Risk ID | B1: Category | C1: Description | D1: Probability | E1: Impact | F1: Risk Score | G1: Risk Level | H1: Mitigation Strategy | I1: Owner | J1: Status | K1: Date Identified | L1: Target Close Date
A2: R-001 | B2: Procurement | C2: Steel procurement delay due to global supply chain disruptions impacting structural steel delivery | D2: 4-High | E2: 5-Critical | F2: =IF(D2="1-Very Low",1,IF(D2="2-Low",2,IF(D2="3-Medium",3,IF(D2="4-High",4,IF(D2="5-Very High",5,0)))))*IF(E2="1-Negligible",1,IF(E2="2-Minor",2,IF(E2="3-Moderate",3,IF(E2="4-Major",4,IF(E2="5-Critical",5,0))))) | G2: =IF(F2>=15,"Critical",IF(F2>=10,"High",IF(F2>=5,"Medium","Low"))) | H2: Pre-order critical steel items early; identify alternative suppliers in Mexico and Canada | I2: Sarah Chen | J2: Open | K2: 45882 | L2: 46007
A3: R-002 | B3: Weather | C3: Unusually heavy rainfall delaying foundation excavation and concrete pour schedule | D3: 3-Medium | E3: 4-Major | F3: =IF(D3="1-Very Low",1,IF(D3="2-Low",2,IF(D3="3-Medium",3,IF(D3="4-High",4,IF(D3="5-Very High",5,0)))))*IF(E3="1-Negligible",1,IF(E3="2-Minor",2,IF(E3="3-Moderate",3,IF(E3="4-Major",4,IF(E3="5-Critical",5,0))))) | G3: =IF(F3>=15,"Critical",IF(F3>=10,"High",IF(F3>=5,"Medium","Low"))) | H3: Install temporary shelter structures; monitor 14-day forecast; add schedule buffer for Q2 | I3: Mike Torres | J3: Open | K3: 45906 | L3: 45949
A4: R-003 | B4: Labor | C4: Labor shortage of skilled ironworkers during peak erection phase | D4: 4-High | E4: 4-Major | F4: =IF(D4="1-Very Low",1,IF(D4="2-Low",2,IF(D4="3-Medium",3,IF(D4="4-High",4,IF(D4="5-Very High",5,0)))))*IF(E4="1-Negligible",1,IF(E4="2-Minor",2,IF(E4="3-Moderate",3,IF(E4="4-Major",4,IF(E4="5-Critical",5,0))))) | G4: =IF(F4>=15,"Critical",IF(F4>=10,"High",IF(F4>=5,"Medium","Low"))) | H4: Partner with local trade unions; offer per-diem incentives; recruit from adjacent states | I4: James Wilson | J4: Open | K4: 45869 | L4: 46008
A5: R-004 | B5: Design | C5: Design change request from owner for expanded concourse width after slab pour | D5: 3-Medium | E5: 3-Moderate | F5: =IF(D5="1-Very Low",1,IF(D5="2-Low",2,IF(D5="3-Medium",3,IF(D5="4-High",4,IF(D5="5-Very High",5,0)))))*IF(E5="1-Negligible",1,IF(E5="2-Minor",2,IF(E5="3-Moderate",3,IF(E5="4-Major",4,IF(E5="5-Critical",5,0))))) | G5: =IF(F5>=15,"Critical",IF(F5>=10,"High",IF(F5>=5,"Medium","Low"))) | H5: Establish formal change order process; require owner sign-off before rework; track impact | I5: Rachel Kim | J5: Open | K5: 45878 | L5: 45936
A6: R-005 | B6: Procurement | C6: Fabrication error in custom steel trusses for roof spanning main arena | D6: 2-Low | E6: 5-Critical | F6: =IF(D6="1-Very Low",1,IF(D6="2-Low",2,IF(D6="3-Medium",3,IF(D6="4-High",4,IF(D6="5-Very High",5,0)))))*IF(E6="1-Negligible",1,IF(E6="2-Minor",2,IF(E6="3-Moderate",3,IF(E6="4-Major",4,IF(E6="5-Critical",5,0))))) | G6: =IF(F6>=15,"Critical",IF(F6>=10,"High",IF(F6>=5,"Medium","Low"))) | H6: Mandate third-party shop drawing review; require mill certification for all steel | I6: Sarah Chen | J6: Open | K6: 45930 | L6: 46088
A7: R-006 | B7: Safety | C7: OSHA fine exposure from fall protection violations on upper deck steel | D7: 2-Low | E7: 4-Major | F7: =IF(D7="1-Very Low",1,IF(D7="2-Low",2,IF(D7="3-Medium",3,IF(D7="4-High",4,IF(D7="5-Very High",5,0)))))*IF(E7="1-Negligible",1,IF(E7="2-Minor",2,IF(E7="3-Moderate",3,IF(E7="4-Major",4,IF(E7="5-Critical",5,0))))) | G7: =IF(F7>=15,"Critical",IF(F7>=10,"High",IF(F7>=5,"Medium","Low"))) | H7: Daily safety briefings; dedicated safety monitor per zone; full-body harness inspection | I7: David Park | J7: Open | K7: 45992 | L7: 46121
A8: R-007 | B8: Labor | C8: Concrete batch plant strike delaying all ready-mix deliveries for 3 weeks | D8: 2-Low | E8: 4-Major | F8: =IF(D8="1-Very Low",1,IF(D8="2-Low",2,IF(D8="3-Medium",3,IF(D8="4-High",4,IF(D8="5-Very High",5,0)))))*IF(E8="1-Negligible",1,IF(E8="2-Minor",2,IF(E8="3-Moderate",3,IF(E8="4-Major",4,IF(E8="5-Critical",5,0))))) | G8: =IF(F8>=15,"Critical",IF(F8>=10,"High",IF(F8>=5,"Medium","Low"))) | H8: Pre-qualify backup batch plant 50 km radius; stockpile 500 CY of aggregate on site | I8: James Wilson | J8: Open | K8: 45926 | L8: 46024
A9: R-008 | B9: Budget | C9: Budget overrun on site utilities relocation — water main and high-voltage lines | D9: 3-Medium | E9: 4-Major | F9: =IF(D9="1-Very Low",1,IF(D9="2-Low",2,IF(D9="3-Medium",3,IF(D9="4-High",4,IF(D9="5-Very High",5,0)))))*IF(E9="1-Negligible",1,IF(E9="2-Minor",2,IF(E9="3-Moderate",3,IF(E9="4-Major",4,IF(E9="5-Critical",5,0))))) | G9: =IF(F9>=15,"Critical",IF(F9>=10,"High",IF(F9>=5,"Medium","Low"))) | H9: Re-estimate utility relocation with civil engineer; request contingency release | I9: Lisa Patel | J9: Open | K9: 45905 | L9: 45950
A10: R-009 | B10: Schedule | C10: Permit delay from city planning department for structural occupancy certificate | D10: 3-Medium | E10: 3-Moderate | F10: =IF(D10="1-Very Low",1,IF(D10="2-Low",2,IF(D10="3-Medium",3,IF(D10="4-High",4,IF(D10="5-Very High",5,0)))))*IF(E10="1-Negligible",1,IF(E10="2-Minor",2,IF(E10="3-Moderate",3,IF(E10="4-Major",4,IF(E10="5-Critical",5,0))))) | G10: =IF(F10>=15,"Critical",IF(F10>=10,"High",IF(F10>=5,"Medium","Low"))) | H10: Hire expediter; submit 2 weeks ahead of schedule; maintain daily follow-up with city | I10: Maria Gonzalez | J10: Open | K10: 45956 | L10: 46109
A11: R-010 | B11: Procurement | C11: Supply chain hold on HVAC rooftop units due to copper coil shortage | D11: 3-Medium | E11: 3-Moderate | F11: =IF(D11="1-Very Low",1,IF(D11="2-Low",2,IF(D11="3-Medium",3,IF(D11="4-High",4,IF(D11="5-Very High",5,0)))))*IF(E11="1-Negligible",1,IF(E11="2-Minor",2,IF(E11="3-Moderate",3,IF(E11="4-Major",4,IF(E11="5-Critical",5,0))))) | G11: =IF(F11>=15,"Critical",IF(F11>=10,"High",IF(F11>=5,"Medium","Low"))) | H11: Order units 8 weeks ahead of need; accept partial shipment with temporary units | I11: Sarah Chen | J11: Open | K11: 45856 | L11: 45898
A12: R-011 | B12: Design | C12: Settlement risk in soil below main column footings discovered during excavation | D12: 2-Low | E12: 5-Critical | F12: =IF(D12="1-Very Low",1,IF(D12="2-Low",2,IF(D12="3-Medium",3,IF(D12="4-High",4,IF(D12="5-Very High",5,0)))))*IF(E12="1-Negligible",1,IF(E12="2-Minor",2,IF(E12="3-Moderate",3,IF(E12="4-Major",4,IF(E12="5-Critical",5,0))))) | G12: =IF(F12>=15,"Critical",IF(F12>=10,"High",IF(F12>=5,"Medium","Low"))) | H12: Complete geotechnical boring analysis before footing design; engineer-reviewed fill spec | I12: Rachel Kim | J12: Mitigated | K12: 45921 | L12: 46012
A13: R-012 | B13: Logistics | C13: Crane mobilization delay due to road weight restrictions on access route | D13: 3-Medium | E13: 3-Moderate | F13: =IF(D13="1-Very Low",1,IF(D13="2-Low",2,IF(D13="3-Medium",3,IF(D13="4-High",4,IF(D13="5-Very High",5,0)))))*IF(E13="1-Negligible",1,IF(E13="2-Minor",2,IF(E13="3-Moderate",3,IF(E13="4-Major",4,IF(E13="5-Critical",5,0))))) | G13: =IF(F13>=15,"Critical",IF(F13>=10,"High",IF(F13>=5,"Medium","Low"))) | H13: Secure oversize load permits 30 days in advance; scout secondary route | I13: Mike Torres | J13: Open | K13: 45911 | L13: 46074
... A31: R-030 | B31: Budget | C31: Premium-time labor costs for weekend pours to recover 6-week schedule delay | D31: 4-High | E31: 3-Moderate | F31: =IF(D31="1-Very Low",1,IF(D31="2-Low",2,IF(D31="3-Medium",3,IF(D31="4-High",4,IF(D31="5-Very High",5,0)))))*IF(E31="1-Negligible",1,IF(E31="2-Minor",2,IF(E31="3-Moderate",3,IF(E31="4-Major",4,IF(E31="5-Critical",5,0))))) | G31: =IF(F31>=15,"Critical",IF(F31>=10,"High",IF(F31>=5,"Medium","Low"))) | H31: Track recovery schedule weekly; cap overtime at 10% of direct labor; pursue EOT from owner | I31: Lisa Patel | J31: Open | K31: 45819 | L31: 45961

Sheet Summary
A1: Risk Level Summary
A2: Risk Level | B2: Count | C2: Percentage
A3: Critical | B3: =COUNTIF('Risk Register'!G:G,A3) | C3: =IF(SUM(B3:B6)>0,B3/SUM(B3:B6),0)
A4: High | B4: =COUNTIF('Risk Register'!G:G,A4) | C4: =IF(SUM(B3:B6)>0,B4/SUM(B3:B6),0)
A5: Medium | B5: =COUNTIF('Risk Register'!G:G,A5) | C5: =IF(SUM(B3:B6)>0,B5/SUM(B3:B6),0)
A6: Low | B6: =COUNTIF('Risk Register'!G:G,A6) | C6: =IF(SUM(B3:B6)>0,B6/SUM(B3:B6),0)
A7: Total | B7: =SUM(B3:B6) | C7: =SUM(C3:C6)
A9: Risk Category Summary
A10: Category | B10: Count | C10: Percentage
A11: Schedule | B11: =COUNTIF('Risk Register'!B:B,A11) | C11: =IF(SUM(B11:B18)>0,B11/SUM(B11:B18),0)
A12: Budget | B12: =COUNTIF('Risk Register'!B:B,A12) | C12: =IF(SUM(B11:B18)>0,B12/SUM(B11:B18),0)
A13: Safety | B13: =COUNTIF('Risk Register'!B:B,A13) | C13: =IF(SUM(B11:B18)>0,B13/SUM(B11:B18),0)
A14: Design | B14: =COUNTIF('Risk Register'!B:B,A14) | C14: =IF(SUM(B11:B18)>0,B14/SUM(B11:B18),0)
A15: Procurement | B15: =COUNTIF('Risk Register'!B:B,A15) | C15: =IF(SUM(B11:B18)>0,B15/SUM(B11:B18),0)
A16: Labor | B16: =COUNTIF('Risk Register'!B:B,A16) | C16: =IF(SUM(B11:B18)>0,B16/SUM(B11:B18),0)
A17: Weather | B17: =COUNTIF('Risk Register'!B:B,A17) | C17: =IF(SUM(B11:B18)>0,B17/SUM(B11:B18),0)
A18: Logistics | B18: =COUNTIF('Risk Register'!B:B,A18) | C18: =IF(SUM(B11:B18)>0,B18/SUM(B11:B18),0)
A19: Total | B19: =SUM(B11:B18) | C19: =SUM(C11:C18)
